pylogpro/__init__.py
pylogpro/level.py
pylogpro/logerctl.py
pylogpro/pylogpro.py
pylogpro-0.0.4.dist-info/LICENSE
pylogpro-0.0.4.dist-info/METADATA
pylogpro-0.0.4.dist-info/WHEEL
pylogpro-0.0.4.dist-info/top_level.txt
pylogpro-0.0.4.dist-info/RECORD
