Metadata-Version: 2.1
Name: pylogpro
Version: 0.0.4
Summary: pylogpro - 更加简洁的python日志记录工具
Home-page: UNKNOWN
Author: 31core
Author-email: zero.mail@foxmail.com
License: Mit License
Platform: UNKNOWN
